MANIFEST.in
README.md
setup.cfg
setup.py
lequangminh/__init__.py
lequangminh.egg-info/PKG-INFO
lequangminh.egg-info/SOURCES.txt
lequangminh.egg-info/dependency_links.txt
lequangminh.egg-info/top_level.txt