Metadata-Version: 2.1
Name: lequangminh
Version: 0.0.1
Summary: by quangminh591, loTus01 and BlueRed
Author-email: <quangminh591@gmail.com>
License: Eclipse Public License 0.0.1
Keywords: cli,fade,colors,terminal,tui
